ydb_dbapi/__init__.py
ydb_dbapi/connections.py
ydb_dbapi/constants.py
ydb_dbapi/cursors.py
ydb_dbapi/errors.py
ydb_dbapi/utils.py
ydb_dbapi/version.py
ydb_dbapi-0.1.18.dist-info/METADATA
ydb_dbapi-0.1.18.dist-info/WHEEL
ydb_dbapi-0.1.18.dist-info/licenses/LICENSE
ydb_dbapi-0.1.18.dist-info/RECORD
