Metadata-Version: 2.4
Name: ydb-dbapi
Version: 0.1.18
Summary: YDB Python DBAPI which complies with PEP 249
License-File: LICENSE
Author: Yandex LLC
Author-email: ydb@yandex-team.ru
Requires-Python: >=3.8,<4.0
Classifier: Programming Language :: Python :: 3
Classifier: Programming Language :: Python :: 3.8
Classifier: Programming Language :: Python :: 3.9
Classifier: Programming Language :: Python :: 3.10
Classifier: Programming Language :: Python :: 3.11
Classifier: Programming Language :: Python :: 3.12
Classifier: Programming Language :: Python :: 3.13
Classifier: Programming Language :: Python :: 3.14
Requires-Dist: ydb (>=3.24.0,<4.0.0)
Project-URL: Repository, https://github.com/ydb-platform/ydb-python-dbapi/
